[
  {
    "line": 2,
    "elements": [
      {
        "start_timestamp": "2021-01-25T16:40:22.419Z",
        "line": 3,
        "name": "Register new users for GMI Bank",
        "description": "",
        "id": "registration;register-new-users-for-gmi-bank",
        "type": "scenario",
        "keyword": "Scenario",
        "steps": [
          {
            "result": {
              "duration": 4528000000,
              "status": "passed"
            },
            "line": 4,
            "name": "user is on the registration page",
            "match": {
              "location": "gmibank.stepdefinitions.RegistrationStepDefinitions.user_is_on_the_registration_page()"
            },
            "keyword": "Given "
          },
          {
            "result": {
              "duration": 253000000,
              "status": "passed"
            },
            "line": 5,
            "name": "user enters ssn number as \"\u003cSSN\u003e\"",
            "match": {
              "arguments": [
                {
                  "val": "\"\u003cSSN\u003e\"",
                  "offset": 26
                }
              ],
              "location": "gmibank.stepdefinitions.RegistrationStepDefinitions.user_enters_ssn_number_as(java.lang.String)"
            },
            "keyword": "And "
          },
          {
            "result": {
              "duration": 343000000,
              "status": "passed"
            },
            "line": 6,
            "name": "user enters firstname and lastname as \"\u003cfirstname\u003e\" and \"\u003clastname\u003e\"",
            "match": {
              "arguments": [
                {
                  "val": "\"\u003cfirstname\u003e\"",
                  "offset": 38
                },
                {
                  "val": "\"\u003clastname\u003e\"",
                  "offset": 56
                }
              ],
              "location": "gmibank.stepdefinitions.RegistrationStepDefinitions.user_enters_firstname_and_lastname_as_and(java.lang.String,java.lang.String)"
            },
            "keyword": "Then "
          },
          {
            "result": {
              "duration": 141000000,
              "status": "passed"
            },
            "line": 7,
            "name": "user provides address \"\u003caddress\u003e\"",
            "match": {
              "arguments": [
                {
                  "val": "\"\u003caddress\u003e\"",
                  "offset": 22
                }
              ],
              "location": "gmibank.stepdefinitions.RegistrationStepDefinitions.user_provides_address(java.lang.String)"
            },
            "keyword": "When "
          },
          {
            "result": {
              "duration": 141000000,
              "status": "passed"
            },
            "line": 8,
            "name": "user provides mobilephone as \"\u003cmobilephone\u003e\"",
            "match": {
              "arguments": [
                {
                  "val": "\"\u003cmobilephone\u003e\"",
                  "offset": 29
                }
              ],
              "location": "gmibank.stepdefinitions.RegistrationStepDefinitions.user_provides_mobilephone_as(java.lang.String)"
            },
            "keyword": "Then "
          },
          {
            "result": {
              "duration": 104000000,
              "status": "passed"
            },
            "line": 9,
            "name": "user provides a username \"\u003cusername\u003e\"",
            "match": {
              "arguments": [
                {
                  "val": "\"\u003cusername\u003e\"",
                  "offset": 25
                }
              ],
              "location": "gmibank.stepdefinitions.RegistrationStepDefinitions.user_provides_a_username(java.lang.String)"
            },
            "keyword": "And "
          },
          {
            "result": {
              "duration": 180000000,
              "status": "passed"
            },
            "line": 10,
            "name": "user provides email id as \"\u003cemail\u003e\"",
            "match": {
              "arguments": [
                {
                  "val": "\"\u003cemail\u003e\"",
                  "offset": 26
                }
              ],
              "location": "gmibank.stepdefinitions.RegistrationStepDefinitions.user_provides_email_id_as(java.lang.String)"
            },
            "keyword": "Then "
          },
          {
            "result": {
              "duration": 148000000,
              "status": "passed"
            },
            "line": 11,
            "name": "user enters the password as \"\u003cfirstpassword\u003e\"",
            "match": {
              "arguments": [
                {
                  "val": "\"\u003cfirstpassword\u003e\"",
                  "offset": 28
                }
              ],
              "location": "gmibank.stepdefinitions.RegistrationStepDefinitions.user_enters_the_password_as(java.lang.String)"
            },
            "keyword": "When "
          },
          {
            "result": {
              "duration": 114000000,
              "status": "passed"
            },
            "line": 12,
            "name": "user confirms the new password \"\u003csecondpassword\u003e\"",
            "match": {
              "arguments": [
                {
                  "val": "\"\u003csecondpassword\u003e\"",
                  "offset": 31
                }
              ],
              "location": "gmibank.stepdefinitions.RegistrationStepDefinitions.user_confirms_the_new_password(java.lang.String)"
            },
            "keyword": "And "
          },
          {
            "result": {
              "duration": 310000000,
              "status": "passed"
            },
            "line": 13,
            "name": "user clicks on register button and sees the success message as \"\u003cmessage\u003e\"",
            "match": {
              "arguments": [
                {
                  "val": "\"\u003cmessage\u003e\"",
                  "offset": 63
                }
              ],
              "location": "gmibank.stepdefinitions.RegistrationStepDefinitions.user_clicks_on_register_button_and_sees_the_success_message_as(java.lang.String)"
            },
            "keyword": "Then "
          }
        ],
        "tags": [
          {
            "name": "@Registration"
          }
        ]
      }
    ],
    "name": "Registration",
    "description": "",
    "id": "registration",
    "keyword": "Feature",
    "uri": "file:src/test/resources/features/registration.feature",
    "tags": [
      {
        "name": "@Registration",
        "type": "Tag",
        "location": {
          "line": 1,
          "column": 1
        }
      }
    ]
  }
]